stocpy/__init__.py
stocpy/cdf_generator.py
stocpy/random_variable.py
stocpy/test.py
stocpy-0.0.4.dist-info/LICENSE.txt
stocpy-0.0.4.dist-info/METADATA
stocpy-0.0.4.dist-info/WHEEL
stocpy-0.0.4.dist-info/top_level.txt
stocpy-0.0.4.dist-info/RECORD
