Metadata-Version: 2.1
Name: stocpy
Version: 0.0.4
Summary: probability theory, stochastic process, finance engineering
Home-page: https://github.com/floating15/stocpy
Author: haoming wang
Author-email: wanghaoming17@163.com
License: UNKNOWN
Platform: UNKNOWN
Classifier: Programming Language :: Python :: 3
Classifier: License :: OSI Approved :: GNU General Public License (GPL)
Requires-Python: >=3
License-File: LICENSE.txt
Requires-Dist: numpy
Requires-Dist: scipy
